setup.py
perfectrand/__init__.py
perfectrand.egg-info/PKG-INFO
perfectrand.egg-info/SOURCES.txt
perfectrand.egg-info/dependency_links.txt
perfectrand.egg-info/not-zip-safe
perfectrand.egg-info/top_level.txt