Metadata-Version: 1.0
Name: perfectrand
Version: 0.1
Summary: The perfect random number generator
Home-page: https://github.com/maral/perfectrand
Author: Marek Lisy
Author-email: marek.lisy@centrum.cz
License: MIT
Platform: UNKNOWN
